bitcoin_keygen/__init__.py
bitcoin_keygen/assoc.py
bitcoin_keygen/base58_check.py
bitcoin_keygen/private_key.py
bitcoin_keygen-0.1.0.dist-info/LICENSE
bitcoin_keygen-0.1.0.dist-info/METADATA
bitcoin_keygen-0.1.0.dist-info/WHEEL
bitcoin_keygen-0.1.0.dist-info/top_level.txt
bitcoin_keygen-0.1.0.dist-info/RECORD
