Metadata-Version: 2.1
Name: bitcoin-keygen
Version: 0.1.0
Summary: Bitcoin Associative Functions
Home-page: https://github.com/cheran-senthil/bitcoin-keygen
Author: Cheran
License: UNKNOWN
Project-URL: Bug Reports, https://github.com/cheran-senthil/bitcoin-keygen/issues
Project-URL: Source, https://github.com/cheran-senthil/bitcoin-keygen/
Keywords: bitcoin keygen python script blockchain cryptography cryptocurrency
Platform: UNKNOWN
Classifier: Development Status :: 4 - Beta
Classifier: License :: OSI Approved :: GNU General Public License v3 (GPLv3)
Classifier: Programming Language :: Python :: 3
Classifier: Programming Language :: Python :: 3.6
Classifier: Programming Language :: Python :: 3.7
